msconvert/__cli.py
msconvert/__init__.py
msconvert/__main__.py
msconvert-1.3.post3.dist-info/LICENSE
msconvert-1.3.post3.dist-info/METADATA
msconvert-1.3.post3.dist-info/WHEEL
msconvert-1.3.post3.dist-info/entry_points.txt
msconvert-1.3.post3.dist-info/top_level.txt
msconvert-1.3.post3.dist-info/RECORD
