Metadata-Version: 2.1
Name: msconvert
Version: 1.3.post3
Summary: A wrapper for the pwiz/msconvert docker container with memory limits and automatic retry.
Author: Falk Boudewijn Schimweg
Author-email: git@falk.schimweg.de
License: GNU Affero General Public License v3 or later (AGPLv3+)
Requires-Python: >=3.10
License-File: LICENSE
